idsmanagment/IdsManagment.py
idsmanagment/IdsManagmentTest.py
idsmanagment/_config/.gitignore
idsmanagment/_config/config.yaml
idsmanagment/_config/config_test.yaml
idsmanagment/samId/SamId.py
idsmanagment/samId/SamIdTest.py
idsmanagment/test/SparkSessionFactory.py
odap_id_managment-0.0.2.dist-info/entry_points.txt
odap_id_managment-0.0.2.dist-info/LICENSE
odap_id_managment-0.0.2.dist-info/WHEEL
odap_id_managment-0.0.2.dist-info/METADATA
odap_id_managment-0.0.2.dist-info/RECORD
