Metadata-Version: 2.1
Name: odap-id-managment
Version: 0.0.2
Summary: IDs managment for ODAP
Home-page: https://github.com/DataSentics/odap-id-managment
License: Proprietary
Author: Datasentics
Author-email: samuel.bajanik@datasentics.com
Requires-Python: >=3.8,<4.0
Classifier: License :: Other/Proprietary License
Classifier: Operating System :: OS Independent
Classifier: Programming Language :: Python :: 3
Classifier: Programming Language :: Python :: 3.8
Classifier: Programming Language :: Python :: 3.9
Classifier: Programming Language :: Python :: 3.10
Classifier: Programming Language :: Python :: 3
Requires-Dist: daipe-core (>=1.4.2,<2.0.0)
Requires-Dist: databricks-bundle (>=1.4.12,<2.0.0)
Requires-Dist: pyfony-bundles (>=0.4.4,<0.5.0)
Project-URL: Repository, https://github.com/DataSentics/odap-id-managment
